tabling/__init__.py
tabling/axis.py
tabling/cell.py
tabling/column.py
tabling/element.py
tabling/py.typed
tabling/row.py
tabling/table.py
tabling/properties/__init__.py
tabling/properties/background.py
tabling/properties/border.py
tabling/properties/font.py
tabling/properties/margin.py
tabling/properties/padding.py
tabling/properties/spacing.py
tabling/properties/text.py
tabling-2.2.1.dist-info/licenses/LICENSE
tabling-2.2.1.dist-info/METADATA
tabling-2.2.1.dist-info/WHEEL
tabling-2.2.1.dist-info/top_level.txt
tabling-2.2.1.dist-info/RECORD
