Metadata-Version: 2.4
Name: tabling
Version: 2.2.1
Summary: Tabling is a Python library, inspired by HTML and CSS, for creating highly customizable tables in the console.
Author-email: "Haripo Wesley T." <haripowesleyt@proton.me>
Maintainer-email: "Haripo Wesley T." <haripowesleyt@proton.me>
License: MIT License
Project-URL: Homepage, https://github.com/haripowesleyt/tabling
Project-URL: Issues, https://github.com/haripowesleyt/tabling/issues
Project-URL: Repository, https://github.com/haripowesleyt/tabling
Keywords: table,tabular
Classifier: Development Status :: 5 - Production/Stable
Classifier: Intended Audience :: Developers
Classifier: Programming Language :: Python :: 3.7
Classifier: Programming Language :: Python :: 3.8
Classifier: Programming Language :: Python :: 3.9
Classifier: Programming Language :: Python :: 3.10
Classifier: Programming Language :: Python :: 3.11
Classifier: Programming Language :: Python :: 3.12
Classifier: Programming Language :: Python :: 3.13
Classifier: License :: OSI Approved :: MIT License
Classifier: Operating System :: OS Independent
Requires-Python: >=3.7
License-File: LICENSE
Requires-Dist: printly>=0.4.0
Dynamic: license-file
